asignals/__init__.py
asignals/signal.py
asignals-1.0.2.dist-info/licenses/LICENCE
asignals-1.0.2.dist-info/METADATA
asignals-1.0.2.dist-info/WHEEL
asignals-1.0.2.dist-info/top_level.txt
asignals-1.0.2.dist-info/RECORD
