Metadata-Version: 2.4
Name: asignals
Version: 1.0.2
Summary: Async signals implementation for Python with type-safe callbacks
Author-email: xmarlon30x2 <xmarlon360x2@gmail.com>
License: MIT License
Project-URL: Homepage, https://github.com/xmarlon30x2/asignals
Project-URL: Repository, https://github.com/xmarlon30x2/asignals
Classifier: Programming Language :: Python :: 3
Classifier: License :: OSI Approved :: MIT License
Classifier: Operating System :: OS Independent
Requires-Python: >=3.13
License-File: LICENCE
Dynamic: license-file
